LICENSE
MANIFEST.in
setup.py
Overseer.egg-info/PKG-INFO
Overseer.egg-info/SOURCES.txt
Overseer.egg-info/dependency_links.txt
Overseer.egg-info/not-zip-safe
Overseer.egg-info/requires.txt
Overseer.egg-info/top_level.txt
example_project/__init__.py
example_project/local_settings.py
example_project/manage.py
example_project/settings.py
example_project/urls.py
overseer/__init__.py
overseer/admin.py
overseer/conf.py
overseer/context_processors.py
overseer/forms.py
overseer/models.py
overseer/urls.py
overseer/utils.py
overseer/views.py
overseer/management/__init__.py
overseer/management/commands/__init__.py
overseer/management/commands/overseer_twitter_auth.py
overseer/media/css/base.css
overseer/media/images/green_light_128x128.png
overseer/media/images/green_light_16x16.png
overseer/media/images/green_light_32x32.png
overseer/media/images/red_light_128x128.png
overseer/media/images/red_light_16x16.png
overseer/media/images/red_light_32x32.png
overseer/media/images/yellow_light_128x128.png
overseer/media/images/yellow_light_16x16.png
overseer/media/images/yellow_light_32x32.png
overseer/migrations/0001_initial.py
overseer/migrations/0002_auto__add_subscription__add_unverifiedsubscription.py
overseer/migrations/__init__.py
overseer/templates/overseer/404.html
overseer/templates/overseer/500.html
overseer/templates/overseer/base.html
overseer/templates/overseer/create_subscription.html
overseer/templates/overseer/create_subscription_complete.html
overseer/templates/overseer/event.html
overseer/templates/overseer/index.html
overseer/templates/overseer/invalid_subscription_token.html
overseer/templates/overseer/service.html
overseer/templates/overseer/subscription_confirmed.html
overseer/templates/overseer/unsubscribe_confirmed.html
overseer/templates/overseer/update_subscription.html
overseer/templatetags/__init__.py
overseer/templatetags/overseer_helpers.py
overseer/tests/__init__.py
overseer/tests/tests.py
overseer/tests/urls.py