Metadata-Version: 1.0
Name: Overseer
Version: 0.2.2
Summary: A status board built with Django
Home-page: http://github.com/disqus/overseer
Author: DISQUS
Author-email: opensource@disqus.com
License: UNKNOWN
Platform: UNKNOWN
Classifier: Framework :: Django
Classifier: Intended Audience :: Developers
Classifier: Intended Audience :: System Administrators
Classifier: Operating System :: OS Independent
Classifier: Topic :: Software Development
